{"id":"4503fd6826b028053c44a26b7c8a3769d38f7859","url":"http://localhost:3000/subscription","source":"self.__next_f.push([1,\":D{\\\"time\\\":23.36906799999997}\\n4a:D\\\"$4b\\\"\\n4a:D{\\\"time\\\":26.353692000000592}\\n4a:[\\\"$\\\",\\\"$L4d\\\",null,{\\\"children\\\":[\\\"$\\\",\\\"$4f\\\",null,{\\\"name\\\":\\\"Next.MetadataOutlet\\\",\\\"children\\\":\\\"$@50\\\"},\\\"$4b\\\",\\\"$4e\\\",1]},\\\"$4b\\\",\\\"$4c\\\",1]\\n52:D{\\\"time\\\":27.69369700000243}\\n52:D\\\"$53\\\"\\n52:D{\\\"time\\\":27.73652200000288}\\n52:null\\n55:D{\\\"time\\\":27.88726200000019}\\n55:D\\\"$56\\\"\\n55:D{\\\"time\\\":28.0956290000031}\\n59:D{\\\"time\\\":28.329618000003393}\\n59:D\\\"$5a\\\"\\n55:[\\\"$\\\",\\\"$L58\\\",null,{\\\"children\\\":\\\"$L59\\\"},\\\"$56\\\",\\\"$57\\\",1]\\n5b:D{\\\"time\\\":29.869455000000016}\\n5b:D\\\"$5c\\\"\\n5b:D{\\\"time\\\":30.11801700000069}\\n61:D{\\\"time\\\":30.46369400000185}\\n61:D\\\"$62\\\"\\n5b:[\\\"$\\\",\\\"div\\\",null,{\\\"hidden\\\":true,\\\"children\\\":[\\\"$\\\",\\\"$L5f\\\",null,{\\\"children\\\":[\\\"$\\\",\\\"$4f\\\",null,{\\\"name\\\":\\\"Next.Metadata\\\",\\\"children\\\":\\\"$L61\\\"},\\\"$5c\\\",\\\"$60\\\",1]},\\\"$5c\\\",\\\"$5e\\\",1]},\\\"$5c\\\",\\\"$5d\\\",1]\\n64:[]\\n\"])"}