{"id":"f1f5e52110e997e0f3eb6f8cfde03552b0008c01","url":"http://localhost:3000/book-session","source":"self.__next_f.push([1,\"me\\\":78.04405200001202}\\n4a:D\\\"$4b\\\"\\n4a:D{\\\"time\\\":81.49903500001528}\\n4a:[\\\"$\\\",\\\"$L4d\\\",null,{\\\"children\\\":[\\\"$\\\",\\\"$4f\\\",null,{\\\"name\\\":\\\"Next.MetadataOutlet\\\",\\\"children\\\":\\\"$@50\\\"},\\\"$4b\\\",\\\"$4e\\\",1]},\\\"$4b\\\",\\\"$4c\\\",1]\\n52:D{\\\"time\\\":82.41061200000695}\\n52:D\\\"$53\\\"\\n52:D{\\\"time\\\":82.43673099999432}\\n52:null\\n55:D{\\\"time\\\":82.57930800001486}\\n55:D\\\"$56\\\"\\n55:D{\\\"time\\\":82.75905500000226}\\n59:D{\\\"time\\\":90.31101100001251}\\n59:D\\\"$5a\\\"\\n55:[\\\"$\\\",\\\"$L58\\\",null,{\\\"children\\\":\\\"$L59\\\"},\\\"$56\\\",\\\"$57\\\",1]\\n5b:D{\\\"time\\\":96.2311650000047}\\n5b:D\\\"$5c\\\"\\n5b:D{\\\"time\\\":96.6284840000153}\\n61:D{\\\"time\\\":100.7667220000003}\\n61:D\\\"$62\\\"\\n5b:[\\\"$\\\",\\\"div\\\",null,{\\\"hidden\\\":true,\\\"children\\\":[\\\"$\\\",\\\"$L5f\\\",null,{\\\"children\\\":[\\\"$\\\",\\\"$4f\\\",null,{\\\"name\\\":\\\"Next.Metadata\\\",\\\"children\\\":\\\"$L61\\\"},\\\"$5c\\\",\\\"$60\\\",1]},\\\"$5c\\\",\\\"$5e\\\",1]},\\\"$5c\\\",\\\"$5d\\\",1]\\n64:[]\\n\"])"}