{"id":"087826144f4032ad239494ddeb200f6a8219ae44","url":"http://localhost:3000/book-session?reschedule=800&subscription=11","source":"self.__next_f.push([1,\"{\\\"time\\\":12.100235000005341}\\n4a:D\\\"$4b\\\"\\n4a:D{\\\"time\\\":19.878585000013118}\\n4a:[\\\"$\\\",\\\"$L4d\\\",null,{\\\"children\\\":[\\\"$\\\",\\\"$4f\\\",null,{\\\"name\\\":\\\"Next.MetadataOutlet\\\",\\\"children\\\":\\\"$@50\\\"},\\\"$4b\\\",\\\"$4e\\\",1]},\\\"$4b\\\",\\\"$4c\\\",1]\\n52:D{\\\"time\\\":20.96846899999946}\\n52:D\\\"$53\\\"\\n52:D{\\\"time\\\":20.99271299999964}\\n52:null\\n55:D{\\\"time\\\":21.104443000003812}\\n55:D\\\"$56\\\"\\n55:D{\\\"time\\\":21.323526000007405}\\n59:D{\\\"time\\\":21.7341860000015}\\n59:D\\\"$5a\\\"\\n55:[\\\"$\\\",\\\"$L58\\\",null,{\\\"children\\\":\\\"$L59\\\"},\\\"$56\\\",\\\"$57\\\",1]\\n5b:D{\\\"time\\\":22.713108000010834}\\n5b:D\\\"$5c\\\"\\n5b:D{\\\"time\\\":22.971813000011025}\\n61:D{\\\"time\\\":23.204527000008966}\\n61:D\\\"$62\\\"\\n5b:[\\\"$\\\",\\\"div\\\",null,{\\\"hidden\\\":true,\\\"children\\\":[\\\"$\\\",\\\"$L5f\\\",null,{\\\"children\\\":[\\\"$\\\",\\\"$4f\\\",null,{\\\"name\\\":\\\"Next.Metadata\\\",\\\"children\\\":\\\"$L61\\\"},\\\"$5c\\\",\\\"$60\\\",1]},\\\"$5c\\\",\\\"$5e\\\",1]},\\\"$5c\\\",\\\"$5d\\\",1]\\n64:[]\\n\"])"}