{"id":"7a76f08a4482b46824d01c794e02f1c88968bff2","url":"http://localhost:3000/login","source":"self.__next_f.push([1,\"$44\\\",1]},\\\"$3d\\\",\\\"$43\\\",1]]},\\\"$3d\\\",\\\"$40\\\",1]},\\\"$3d\\\",\\\"$3f\\\",1]]\\n46:D{\\\"time\\\":45.65727799999877}\\n46:D\\\"$47\\\"\\n46:D{\\\"time\\\":47.78684499999508}\\n4d:D{\\\"time\\\":49.31920500000706}\\n4d:D\\\"$4e\\\"\\n4d:D{\\\"time\\\":49.523569000011776}\\n4d:[\\\"$\\\",\\\"$L50\\\",null,{\\\"href\\\":\\\"/\\\",\\\"className\\\":\\\"text-sm text-kore-gray-dark/50 hover:text-kore-red transition-colors\\\",\\\"children\\\":\\\"Inicio\\\"},\\\"$4e\\\",\\\"$4f\\\",1]\\n52:D{\\\"time\\\":49.87927599999239}\\n52:D\\\"$53\\\"\\n52:D{\\\"time\\\":50.017917999997735}\\n52:[\\\"$\\\",\\\"$L50\\\",null,{\\\"href\\\":\\\"/kore-brand\\\",\\\"className\\\":\\\"text-sm text-kore-gray-dark/50 hover:text-kore-red transition-colors\\\",\\\"children\\\":\\\"La Marca\\\"},\\\"$53\\\",\\\"$54\\\",1]\\n56:D{\\\"time\\\":50.79485000000568}\\n56:D\\\"$57\\\"\\n56:D{\\\"time\\\":51.25422199998866}\\n56:[\\\"$\\\",\\\"$L50\\\",null,{\\\"href\\\":\\\"/programs\\\",\\\"className\\\":\\\"text-sm text-kore-gray-dark/50 hover:text-kore-red transition-colors\\\",\\\"children\\\":\\\"Programas\\\"},\\\"$57\\\",\\\"$58\\\",1]\\n5a:D{\\\"time\\\":52.35711899999296}\\n5a:D\\\"$5b\\\"\\n5a:D{\\\"time\\\":52.580538999987766}\\n5a:[\\\"$\\\",\\\"$L50\\\",null,{\\\"href\\\":\\\"/faq\\\",\\\"className\\\":\\\"text-sm text-kore-gray-dark/50 hover:text-kore-red transition-colors\\\",\\\"children\\\":\\\"FAQ\\\"},\\\"$5b\\\",\\\"$5c\\\",1]\\n5e:D{\\\"time\\\":53.53607699999702}\\n5e:D\\\"$5f\\\"\\n5e:D{\\\"time\\\":54.30620500000077}\\n5e:[\\\"$\\\",\\\"$L50\\\",null,{\\\"href\\\":\\\"/contact\\\",\\\"className\\\":\\\"text-sm text-kore-gray-dark/50 hover:text-kore-red transition-colors\\\",\\\"children\\\":\\\"Contacto\\\"},\\\"$5f\\\",\\\"$60\\\",1]\\n\"])"}